adjust_precision_for_schema/__init__.py
adjust_precision_for_schema/schema_adjuster.py
adjust_precision_for_schema-0.3.4.dist-info/WHEEL
adjust_precision_for_schema-0.3.4.dist-info/METADATA
adjust_precision_for_schema-0.3.4.dist-info/RECORD
