Metadata-Version: 2.1
Name: adjust-precision-for-schema
Version: 0.3.4
Summary: Intended for use in singer-io targets to overcome the precision differences among certain data source systems, Python, and target systems
License: MIT
Author: Datateer
Author-email: dev@datateer.com
Requires-Python: >=3.8,<4.0
Classifier: License :: OSI Approved :: MIT License
Classifier: Programming Language :: Python :: 3
Classifier: Programming Language :: Python :: 3.10
Classifier: Programming Language :: Python :: 3.8
Classifier: Programming Language :: Python :: 3.9
Requires-Dist: jsonschema (>=2.6.0)
